hermes/LICENSE
hermes/__init__.py
hermes/cli.py
hermes/__pycache__/__init__.cpython-312.pyc
hermes/__pycache__/cli.cpython-312.pyc
hermes/core/__init__.py
hermes/core/global_vars.py
hermes/core/models.py
hermes/core/__pycache__/__init__.cpython-312.pyc
hermes/core/__pycache__/global_vars.cpython-312.pyc
hermes/core/__pycache__/models.cpython-312.pyc
hermes/internal/__init__.py
hermes/internal/app.py
hermes/internal/funcs.py
hermes/internal/keys.py
hermes/internal/parser.py
hermes/internal/server.py
hermes/internal/setup.py
hermes/internal/__pycache__/__init__.cpython-312.pyc
hermes/internal/__pycache__/app.cpython-312.pyc
hermes/internal/__pycache__/deploy.cpython-312.pyc
hermes/internal/__pycache__/funcs.cpython-312.pyc
hermes/internal/__pycache__/keys.cpython-312.pyc
hermes/internal/__pycache__/parser.cpython-312.pyc
hermes/internal/__pycache__/setup.cpython-312.pyc
hermes/services/__init__.py
hermes/services/connect.py
hermes/services/deploy.py
hermes/services/events.py
hermes/services/getters.py
hermes/services/init.py
hermes/services/migrate.py
hermes/services/providers.json
hermes/services/server_config.py
hermes/services/__pycache__/__init__.cpython-312.pyc
hermes/services/__pycache__/connect.cpython-312.pyc
hermes/services/__pycache__/deploy.cpython-312.pyc
hermes/services/__pycache__/events.cpython-312.pyc
hermes/services/__pycache__/getters.cpython-312.pyc
hermes_deployer-0.3.1.dist-info/licenses/LICENSE
hermes_deployer-0.3.1.dist-info/METADATA
hermes_deployer-0.3.1.dist-info/WHEEL
hermes_deployer-0.3.1.dist-info/entry_points.txt
hermes_deployer-0.3.1.dist-info/top_level.txt
hermes_deployer-0.3.1.dist-info/RECORD
