Metadata-Version: 2.4
Name: hermes-deployer
Version: 0.3.1
Summary: Multi-Server, Multi-App, Multi-Service Orchestrator.
Author: Steven Mendoza
License: MIT
Project-URL: Homepage, https://github.com/StevenMZH/DHermes.git
Project-URL: Documentation, https://github.com/StevenMZH/DHermes.git
Project-URL: Source, https://github.com/StevenMZH/DHermes.git
Project-URL: Issues, https://github.com/StevenMZH/DHermes.git/issues
Keywords: DevOps,deployment,infrastructure-as-code,yaml,multi-server,automation
Requires-Python: >=3.7
License-File: LICENSE
Requires-Dist: bcrypt==4.3.0
Requires-Dist: cffi==1.17.1
Requires-Dist: click==8.2.1
Requires-Dist: colorama==0.4.6
Requires-Dist: cryptography==45.0.2
Requires-Dist: dotenv==0.9.9
Requires-Dist: paramiko==3.5.1
Requires-Dist: pycparser==2.22
Requires-Dist: PyNaCl==1.5.0
Requires-Dist: python-dotenv==1.1.0
Requires-Dist: PyYAML==6.0.2
Dynamic: license-file
